trueentropy/__init__.py
trueentropy/_accel.pyx
trueentropy/accel.py
trueentropy/aio.py
trueentropy/collector.py
trueentropy/config.py
trueentropy/health.py
trueentropy/hybrid.py
trueentropy/lazy.py
trueentropy/persistence.py
trueentropy/pool.py
trueentropy/pools.py
trueentropy/py.typed
trueentropy/tap.py
trueentropy/harvesters/__init__.py
trueentropy/harvesters/base.py
trueentropy/harvesters/external.py
trueentropy/harvesters/network.py
trueentropy/harvesters/radioactive.py
trueentropy/harvesters/system.py
trueentropy/harvesters/timing.py
trueentropy/harvesters/weather.py
trueentropy-0.2.0.dist-info/METADATA
trueentropy-0.2.0.dist-info/WHEEL
trueentropy-0.2.0.dist-info/licenses/LICENSE
trueentropy-0.2.0.dist-info/RECORD
