Metadata-Version: 2.4
Name: trueentropy
Version: 0.2.0
Summary: True randomness from real-world entropy sources - harness chaos from network latency, system jitter, seismic activity, and financial markets
Project-URL: Homepage, https://github.com/medeirosdev/TrueEntropy-PyLib
Project-URL: Documentation, https://github.com/medeirosdev/TrueEntropy-PyLib#readme
Project-URL: Repository, https://github.com/medeirosdev/TrueEntropy-PyLib
Project-URL: Issues, https://github.com/medeirosdev/TrueEntropy-PyLib/issues
Project-URL: Changelog, https://github.com/medeirosdev/TrueEntropy-PyLib/blob/main/CHANGELOG.md
Author: TrueEntropy Contributors
License-Expression: MIT
License-File: LICENSE
Keywords: chaos,cryptography,entropy,hardware-random,random,rng,security,true-random
Classifier: Development Status :: 4 - Beta
Classifier: Intended Audience :: Developers
Classifier: Intended Audience :: Science/Research
Classifier: License :: OSI Approved :: MIT License
Classifier: Operating System :: OS Independent
Classifier: Programming Language :: Python :: 3
Classifier: Programming Language :: Python :: 3.9
Classifier: Programming Language :: Python :: 3.10
Classifier: Programming Language :: Python :: 3.11
Classifier: Programming Language :: Python :: 3.12
Classifier: Programming Language :: Python :: 3.13
Classifier: Topic :: Scientific/Engineering
Classifier: Topic :: Security :: Cryptography
Classifier: Topic :: Software Development :: Libraries :: Python Modules
Classifier: Typing :: Typed
Requires-Python: >=3.9
Requires-Dist: psutil>=5.8.0
Requires-Dist: requests>=2.25.0
Provides-Extra: all
Requires-Dist: black>=23.0; extra == 'all'
Requires-Dist: cython>=3.0; extra == 'all'
Requires-Dist: mkdocs-material>=9.0; extra == 'all'
Requires-Dist: mkdocs>=1.5; extra == 'all'
Requires-Dist: mkdocstrings[python]>=0.24; extra == 'all'
Requires-Dist: mypy>=1.0; extra == 'all'
Requires-Dist: pytest-asyncio>=0.21; extra == 'all'
Requires-Dist: pytest-cov>=4.0; extra == 'all'
Requires-Dist: pytest>=7.0; extra == 'all'
Requires-Dist: ruff>=0.1.0; extra == 'all'
Requires-Dist: setuptools>=65.0; extra == 'all'
Requires-Dist: types-psutil; extra == 'all'
Requires-Dist: types-requests; extra == 'all'
Provides-Extra: cython
Requires-Dist: cython>=3.0; extra == 'cython'
Requires-Dist: setuptools>=65.0; extra == 'cython'
Provides-Extra: dev
Requires-Dist: black>=23.0; extra == 'dev'
Requires-Dist: mypy>=1.0; extra == 'dev'
Requires-Dist: pytest-asyncio>=0.21; extra == 'dev'
Requires-Dist: pytest-cov>=4.0; extra == 'dev'
Requires-Dist: pytest>=7.0; extra == 'dev'
Requires-Dist: ruff>=0.1.0; extra == 'dev'
Requires-Dist: types-psutil; extra == 'dev'
Requires-Dist: types-requests; extra == 'dev'
Provides-Extra: docs
Requires-Dist: mkdocs-material>=9.0; extra == 'docs'
Requires-Dist: mkdocs>=1.5; extra == 'docs'
Requires-Dist: mkdocstrings[python]>=0.24; extra == 'docs'
